{
  "schemaVersion": 1,
  "id": "pvpoption",
  "version": "${version}",
  "name": "pvpOption",
  "description": "Opt-in PvP flagging system. Only players flagged for PvP can deal and take damage from each other.",
  "authors": ["LunixiaLIVE"],
  "contact": {
    "sources": "https://github.com/LunixiaLIVE/pvpOption_1.21.11"
  },
  "license": "MIT",
  "environment": "*",
  "entrypoints": {
    "main": [
      "net.lunix.pvpoption.PvpOption"
    ]
  },
  "mixins": [
    "pvpoption.mixins.json"
  ],
  "depends": {
    "fabricloader": ">=${loader_version}",
    "fabric-api": "*",
    "minecraft": "${minecraft_version}"
  }
}
